result_portal_lib/__init__.py
result_portal_lib/aws_utils.py
result_portal_lib/complaint_manager.py
result_portal_lib/models.py
result_portal_lib-0.2.0.dist-info/METADATA
result_portal_lib-0.2.0.dist-info/WHEEL
result_portal_lib-0.2.0.dist-info/top_level.txt
result_portal_lib-0.2.0.dist-info/RECORD
