Metadata-Version: 2.1
Name: result-portal-lib
Version: 0.2.0
Summary: A library for AWS integration with Django
Home-page: https://github.com/yourusername/result-portal-lib
Author: Adams Animashaun
Author-email: animashaunadams@gmail.com
License: UNKNOWN
Platform: UNKNOWN
Classifier: Programming Language :: Python :: 3
Classifier: License :: OSI Approved :: MIT License
Classifier: Operating System :: OS Independent
Requires-Python: >=3.6
Requires-Dist: boto3>=1.18.63
Requires-Dist: django>=3.2
